domnibus
