Metadata-Version: 1.1
Name: domnibus
Version: 1.0.4
Summary: Get all possible information about a domain
Home-page: https://github.com/cyriac/domnibus
Author: cyriac
Author-email: me@cyriacthomas.com
License: MIT
Download-URL: https://github.com/cyriac/domnibus/archive/v1.0.4.tar.gz
Keywords: domnibus,domni,whois,ssl,nameserver,dns
Platform: UNKNOWN
